Metadata-Version: 2.1
Name: ADwin
Version: 0.18.1
Summary: ADwin API wrapper
Home-page: http://www.ADwin.de
Author: Markus Borchers
Maintainer: Jaeger Computergesteuerte Messtechnik GmbH
Maintainer-email: info@ADwin.de
License: Apache License 2.0
Platform: linux2, win32, darwin
License-File: LICENSE.txt
Requires-Dist: setuptools
Requires-Dist: wheel
